etom/__init__.py
etom/core.py
etom-0.4.2.dist-info/LICENSE
etom-0.4.2.dist-info/METADATA
etom-0.4.2.dist-info/WHEEL
etom-0.4.2.dist-info/RECORD
