Metadata-Version: 2.1
Name: etom
Version: 0.4.2
Summary: A simple project to deal with encrypted toml files
Home-page: https://github.com/JasonLovesDoggo/etom
License: GPLv3
Keywords: toml,encryption,decryption
Author: Jason
Author-email: git@jasoncameron.dev
Requires-Python: >=3.8.1,<4.0
Classifier: License :: Other/Proprietary License
Classifier: Programming Language :: Python :: 3
Classifier: Programming Language :: Python :: 3.9
Classifier: Programming Language :: Python :: 3.10
Classifier: Programming Language :: Python :: 3.11
Classifier: Programming Language :: Python :: 3.12
Requires-Dist: cryptography (>=43.0.0,<44.0.0)
Requires-Dist: toml (>=0.10.2,<0.11.0)
Project-URL: Repository, https://github.com/JasonLovesDoggo/etom
